orca_common/__init__.py
orca_common/api_types.py
orca_common/constants.py
orca_common/embedding_models.py
orca_common/numeric_type.py
orca_common-0.1.4.dist-info/METADATA
orca_common-0.1.4.dist-info/WHEEL
orca_common-0.1.4.dist-info/RECORD
